fastlapmap/__init__.py
fastlapmap/ann.py
fastlapmap/benchmark.py
fastlapmap/similarities.py
fastlapmap/spectral.py
fastlapmap-0.1.2.dist-info/LICENSE
fastlapmap-0.1.2.dist-info/METADATA
fastlapmap-0.1.2.dist-info/WHEEL
fastlapmap-0.1.2.dist-info/top_level.txt
fastlapmap-0.1.2.dist-info/RECORD
