Metadata-Version: 2.1
Name: fastlapmap
Version: 0.1.2
Summary: Fast Laplacian Eigenmaps for dimensionality reduction.
Home-page: https://github.com/davisidarta/fastlapmap
Author: Davi Sidarta-Oliveira
Author-email: davisidarta@fcm.unicamp.br
License: MIT
Project-URL: Bug Tracker, https://github.com/davisidarta/fastlapmap/issues
Platform: UNKNOWN
Classifier: Programming Language :: Python :: 3
Classifier: License :: OSI Approved :: MIT License
Classifier: Operating System :: OS Independent
Requires-Python: >=3.6
License-File: LICENSE
